LICENSE
README.md
pyproject.toml
src/pydantic_mini/__init__.py
src/pydantic_mini/base.py
src/pydantic_mini/exceptions.py
src/pydantic_mini/formatters.py
src/pydantic_mini/py.typed
src/pydantic_mini/typing.py
src/pydantic_mini/utils.py
src/pydantic_mini.egg-info/PKG-INFO
src/pydantic_mini.egg-info/SOURCES.txt
src/pydantic_mini.egg-info/dependency_links.txt
src/pydantic_mini.egg-info/requires.txt
src/pydantic_mini.egg-info/top_level.txt
tests/test_base.py
tests/test_formatter.py
tests/test_forward_ref.py
tests/test_typing.py