Metadata-Version: 2.4
Name: pydantic_mini
Version: 1.2.0
Summary: Dataclass with validation
Author-email: nshaibu <nafiushaibu1@gmail.com>
License:                     GNU GENERAL PUBLIC LICENSE
Project-URL: Issue Tracker, https://github.com/nshaibu/pydantic-mini/issues
Project-URL: CI, https://github.com/nshaibu/pydantic-mini/actions
Keywords: pydantic-mini,pydantic_mini,Schema,ORM,dataclass,pydantic,data-validation,simple,dataclass with vaidation,Data Serialisation,Serialisation
Classifier: Development Status :: 5 - Production/Stable
Classifier: Environment :: Console
Classifier: Intended Audience :: Developers
Classifier: License :: OSI Approved :: GNU General Public License v3 (GPLv3)
Classifier: Operating System :: OS Independent
Classifier: Programming Language :: Python
Classifier: Programming Language :: Python :: 3
Classifier: Programming Language :: Python :: 3.8
Classifier: Programming Language :: Python :: 3.9
Classifier: Programming Language :: Python :: 3.10
Classifier: Programming Language :: Python :: 3.11
Classifier: Programming Language :: Python :: 3.12
Classifier: Programming Language :: Python :: 3.13
Classifier: Topic :: Software Development :: Libraries :: Python Modules
Requires-Python: >=3.8
License-File: LICENSE
Requires-Dist: typing-extensions==4.12.2
Provides-Extra: dev
Requires-Dist: coverage>=7.4.1; extra == "dev"
Requires-Dist: iniconfig==2.0.0; extra == "dev"
Requires-Dist: packaging==24.2; extra == "dev"
Requires-Dist: pluggy==1.5.0; extra == "dev"
Requires-Dist: pytest==8.3.4; extra == "dev"
Requires-Dist: pyflakes==3.2.0; extra == "dev"
Requires-Dist: mccabe==0.7.0; extra == "dev"
Requires-Dist: flake8==7.1.1; extra == "dev"
Requires-Dist: pycodestyle==2.12.1; extra == "dev"
Requires-Dist: flake8-black==0.3.6; extra == "dev"
Requires-Dist: black>=22.1.0; extra == "dev"
Requires-Dist: click==8.1.8; extra == "dev"
Requires-Dist: mypy-extensions==1.0.0; extra == "dev"
Requires-Dist: pathspec==0.12.1; extra == "dev"
Requires-Dist: platformdirs==4.3.6; extra == "dev"
Dynamic: license-file
